ooba_api/__init__.py
ooba_api/clients.py
ooba_api/model_info.py
ooba_api/parameters.py
ooba_api/prompts.py
ooba_api/py.typed
ooba_api/pydantic_compat.py
ooba_api_client-0.1.0a4.dist-info/LICENSE
ooba_api_client-0.1.0a4.dist-info/METADATA
ooba_api_client-0.1.0a4.dist-info/WHEEL
ooba_api_client-0.1.0a4.dist-info/RECORD
