Metadata-Version: 2.1
Name: ooba-api-client
Version: 0.1.0a4
Summary: API Client for Ooba Booga's Text Generation WebUI
Author: James Hutchison
Author-email: jamesghutchison@proton.me
Requires-Python: >=3.10,<4.0
Classifier: Programming Language :: Python :: 3
Classifier: Programming Language :: Python :: 3.10
Classifier: Programming Language :: Python :: 3.11
Requires-Dist: pydantic
Requires-Dist: requests
Requires-Dist: types-requests
